{  
   "img":"http://ghk.h-cdn.co/assets/15/41/980x655/gallery-1444163618-stocking-banner.jpg",
   "title":"",
   "type":"content",
   "list":[  
      {  
         "type":"text",
         "text":"http://ghk.h-cdn.co/assets/15/41/480x720/gallery-1444164073-noel-door.jpg"
      },
      {  
         "type":"image",
         "url":"http://ghk.h-cdn.co/assets/15/41/480x632/gallery-1444164286-framed-christmas-card-display-2.jpg"
      },
      {  
         "type":"text",
         "text":"Who says food can't double as decor? To add warmth to your home, create a cocoa brewing station, made complete with mugs, stirrers and a dispenser."
      },
      {  
         "type":"image",
         "url":"http://ghk.h-cdn.co/assets/15/41/480x720/gallery-1444164757-hot-cocoa.jpg"
      },
      {  
         "type":"text",
         "text":"A miniature display of Santa Claus and his reindeer looks especially fun on some fake snow."
      },
      {  
         "type":"image",
         "url":"http://ghk.h-cdn.co/assets/15/41/480x709/gallery-1444164939-santa-tabletop.png"
      },
      {  
         "type":"text",
         "text":"This blogger got into the spirit by drawing up a beautiful Christmas tree on her chalkboard wall (and we love her door-frame garland, too!)."
      },
      {  
         "type":"image",
         "url":"http://ghk.h-cdn.co/assets/15/41/480x735/gallery-1444165245-chalkboard-tree.jpg"
      },
      {  
         "type":"text",
         "text":"Instead of a traditional sign that reads \"Joy\", replace the 'O' with a wreath that incorporates all colors of the holiday."
      },
      {  
         "type":"image",
         "url":"http://ghk.h-cdn.co/assets/15/41/480x720/gallery-1444165391-joy-sign.jpg"
      },
      {  
         "type":"text",
         "text":"This blogger devoted the space in front of her decked-out mirror to her beautiful collection of angel statues."
      },
      {  
         "type":"image",
         "url":"http://ghk.h-cdn.co/assets/15/41/480x551/gallery-1444165497-christmas-mirror.jpg"
      },
      {  
         "type":"text",
         "text":"Who needs a real tree (or even a fake one)? Pull of a dazzling display with just a few pretty ornaments."
      },
      {  
         "type":"image",
         "url":"http://ghk.h-cdn.co/assets/15/41/480x576/gallery-1444165699-christmas-ornament-tree-on-chevron-stripe-pallet.jpg"
      }
      
   ]
}